CHANGES.md
LICENSE
MANIFEST.in
README.md
setup.py
tango_capo/__init__.py
tango_capo.egg-info/PKG-INFO
tango_capo.egg-info/SOURCES.txt
tango_capo.egg-info/dependency_links.txt
tango_capo.egg-info/not-zip-safe
tango_capo.egg-info/top_level.txt
tango_capo/static/css/events.css
tango_capo/static/css/gallery.css
tango_capo/static/css/print.css
tango_capo/static/css/site.css
tango_capo/static/css/themes/dark.css
tango_capo/static/css/themes/default.css
tango_capo/static/css/themes/light.css
tango_capo/static/css/themes/vert.css
tango_capo/static/fonts/capo_icons_5.eot
tango_capo/static/fonts/capo_icons_5.svg
tango_capo/static/fonts/capo_icons_5.ttf
tango_capo/static/fonts/capo_icons_5.woff
tango_capo/static/fonts/emoticons/emoticons.eot
tango_capo/static/fonts/emoticons/emoticons.svg
tango_capo/static/fonts/emoticons/emoticons.ttf
tango_capo/static/fonts/emoticons/emoticons.woff
tango_capo/static/img/site/1180.jpg
tango_capo/static/img/site/740.jpg
tango_capo/static/img/site/940.jpg
tango_capo/static/img/site/tango_bg.jpg
tango_capo/static/img/site/texture-overlay.png
tango_capo/static/img/site/grids/770.png
tango_capo/static/js/site-combined-min.js
tango_capo/static/source/core_sass/print.scss
tango_capo/static/source/core_sass/site.scss
tango_capo/static/source/core_sass/assets/_all_assets.scss
tango_capo/static/source/core_sass/assets/_button.scss
tango_capo/static/source/core_sass/assets/_calendar.scss
tango_capo/static/source/core_sass/assets/_forms.scss
tango_capo/static/source/core_sass/assets/_grids.scss
tango_capo/static/source/core_sass/assets/_icons.scss
tango_capo/static/source/core_sass/assets/_lists.scss
tango_capo/static/source/core_sass/assets/_pagination.scss
tango_capo/static/source/core_sass/assets/_sideheads.scss
tango_capo/static/source/core_sass/assets/_slideshow.scss
tango_capo/static/source/core_sass/assets/_tables.scss
tango_capo/static/source/core_sass/assets/_tabs.scss
tango_capo/static/source/core_sass/assets/hot-button/_config.scss
tango_capo/static/source/core_sass/assets/hot-button/_gradient.scss
tango_capo/static/source/core_sass/assets/hot-button/_vars.scss
