Metadata-Version: 1.0
Name: tango-capo
Version: 0.3.2
Summary: Capo for Django.
Home-page: https://github.com/tBaxter/tango-capo
Author: Tim Baxter
Author-email: mail.baxter@gmail.com
License: LICENCE.txt
Platform: UNKNOWN
